pycrm/__init__.py
pycrm/plotting.py
pycrm/datasets/__init__.py
pycrm-0.1.0.dist-info/METADATA
pycrm-0.1.0.dist-info/RECORD
pycrm-0.1.0.dist-info/WHEEL
pycrm-0.1.0.dist-info/top_level.txt
