Metadata-Version: 2.1
Name: pycrm
Version: 0.1.0
Summary: CRM analysis functions
Home-page: https://github.com/pfcor/pycrm
Author: Pedro Correia
Author-email: pedrocorreia.rs@gmail.com
License: MIT
Platform: UNKNOWN
Classifier: Development Status :: 2 - Pre-Alpha
Classifier: License :: OSI Approved :: MIT License
Classifier: Programming Language :: Python
Classifier: Programming Language :: Python :: 3
Classifier: Programming Language :: Python :: 3.4
Classifier: Programming Language :: Python :: 3.5
Classifier: Programming Language :: Python :: 3.6
Classifier: Programming Language :: Python :: 3.7
